bin/utils/multi-bleu.perl
texar/torch/__init__.py
texar/torch/hyperparams.py
texar/torch/module_base.py
texar/torch/version.py
texar/torch/core/__init__.py
texar/torch/core/attention_mechanism.py
texar/torch/core/attention_mechanism_utils.py
texar/torch/core/cell_wrappers.py
texar/torch/core/layers.py
texar/torch/core/optimization.py
texar/torch/core/regularizers.py
texar/torch/custom/__init__.py
texar/torch/custom/activation.py
texar/torch/custom/distributions.py
texar/torch/custom/initializers.py
texar/torch/data/__init__.py
texar/torch/data/data_utils.py
texar/torch/data/embedding.py
texar/torch/data/vocabulary.py
texar/torch/data/data/__init__.py
texar/torch/data/data/data_base.py
texar/torch/data/data/data_iterators.py
texar/torch/data/data/data_iterators_utils.py
texar/torch/data/data/dataset_utils.py
texar/torch/data/data/mono_text_data.py
texar/torch/data/data/multi_aligned_data.py
texar/torch/data/data/paired_text_data.py
texar/torch/data/data/record_data.py
texar/torch/data/data/sampler.py
texar/torch/data/data/scalar_data.py
texar/torch/data/data/text_data_base.py
texar/torch/data/tokenizers/__init__.py
texar/torch/data/tokenizers/bert_tokenizer.py
texar/torch/data/tokenizers/bert_tokenizer_utils.py
texar/torch/data/tokenizers/gpt2_tokenizer.py
texar/torch/data/tokenizers/gpt2_tokenizer_utils.py
texar/torch/data/tokenizers/roberta_tokenizer.py
texar/torch/data/tokenizers/sentencepiece_tokenizer.py
texar/torch/data/tokenizers/t5_tokenizer.py
texar/torch/data/tokenizers/tokenizer_base.py
texar/torch/data/tokenizers/xlnet_tokenizer.py
texar/torch/distributed/__init__.py
texar/torch/distributed/data.py
texar/torch/distributed/parallel.py
texar/torch/evals/__init__.py
texar/torch/evals/bleu.py
texar/torch/evals/bleu_moses.py
texar/torch/evals/bleu_transformer.py
texar/torch/evals/metrics.py
texar/torch/losses/__init__.py
texar/torch/losses/adv_losses.py
texar/torch/losses/entropy.py
texar/torch/losses/info_loss.py
texar/torch/losses/losses_utils.py
texar_pytorch-0.1.4.dist-info/LICENSE
texar_pytorch-0.1.4.dist-info/METADATA
texar_pytorch-0.1.4.dist-info/WHEEL
texar_pytorch-0.1.4.dist-info/top_level.txt
texar_pytorch-0.1.4.dist-info/RECORD
