Metadata-Version: 2.1
Name: texar-pytorch
Version: 0.1.4
Summary: Toolkit for Machine Learning and Text Generation
Home-page: https://github.com/asyml/texar-pytorch
License: Apache License Version 2.0
Platform: any
Classifier: Intended Audience :: Developers
Classifier: Intended Audience :: Education
Classifier: Intended Audience :: Science/Research
Classifier: Operating System :: OS Independent
Classifier: Programming Language :: Python
Classifier: Programming Language :: Python :: 3.6
Classifier: Programming Language :: Python :: 3.7
License-File: LICENSE
Requires-Dist: regex (>=2018.01.10)
Requires-Dist: numpy (>=1.16.6)
Requires-Dist: requests
Requires-Dist: funcsigs
Requires-Dist: sentencepiece (>=0.1.96)
Requires-Dist: mypy-extensions
Requires-Dist: packaging (>=19.0)
Requires-Dist: six
Requires-Dist: asyml-utilities (>=0.0.1.dev1)
Provides-Extra: dist
Requires-Dist: adaptdl (>=0.2.4) ; extra == 'dist'
Provides-Extra: examples
Provides-Extra: extras
Requires-Dist: Pillow (>=3.0) ; extra == 'extras'
Requires-Dist: tensorboardX (>=1.8) ; extra == 'extras'
Requires-Dist: six (>=1.15) ; extra == 'extras'
Provides-Extra: torch
Requires-Dist: torch (>=1.0.0) ; extra == 'torch'
